btc_hd_wallet/__init__.py
btc_hd_wallet/base_wallet.py
btc_hd_wallet/bech32.py
btc_hd_wallet/bip32.py
btc_hd_wallet/bip39.py
btc_hd_wallet/bip85.py
btc_hd_wallet/helper.py
btc_hd_wallet/keys.py
btc_hd_wallet/op.py
btc_hd_wallet/paper_wallet.py
btc_hd_wallet/script.py
btc_hd_wallet/wallet_utils.py
btc_hd_wallet/bip39_wordlist/__init__.py
btc_hd_wallet-0.1.1.dist-info/LICENSE
btc_hd_wallet-0.1.1.dist-info/METADATA
btc_hd_wallet-0.1.1.dist-info/WHEEL
btc_hd_wallet-0.1.1.dist-info/top_level.txt
btc_hd_wallet-0.1.1.dist-info/RECORD
