Metadata-Version: 2.1
Name: btc-hd-wallet
Version: 0.1.1
Summary: Bitcoin HD paper wallet implementation.
Home-page: https://github.com/scgbckbone/btc-hd-wallet
Author: Andrej Virgovic
Author-email: virgovica@gmail.com
License: MIT
Keywords: bitcoin,btc,hierarchical deterministic wallet,BIP32,BIP85,BIP39
Platform: UNKNOWN
Classifier: Development Status :: 4 - Beta
Classifier: Programming Language :: Python :: 3 :: Only
Classifier: Programming Language :: Python :: 3.5
Classifier: Programming Language :: Python :: 3.6
Classifier: Programming Language :: Python :: 3.7
Classifier: Programming Language :: Python :: 3.8
Classifier: Programming Language :: Python :: 3.9
Requires-Dist: ecdsa (>=0.15)
